sprynger/__init__.py
sprynger/base.py
sprynger/exceptions.py
sprynger/meta.py
sprynger/metadata.py
sprynger/openaccess.py
sprynger/openaccess_article.py
sprynger/openaccess_chapter.py
sprynger/retrieve.py
sprynger/tests/__init__.py
sprynger/tests/test_exceptions.py
sprynger/tests/test_meta.py
sprynger/tests/test_metadata.py
sprynger/tests/test_openaccess.py
sprynger/tests/test_retrieve.py
sprynger/tests/test_startup.py
sprynger/utils/__init__.py
sprynger/utils/constants.py
sprynger/utils/data_structures.py
sprynger/utils/fetch.py
sprynger/utils/parse.py
sprynger/utils/parse_openaccess.py
sprynger/utils/startup.py
sprynger-0.4.1.dist-info/licenses/LICENSE
sprynger-0.4.1.dist-info/METADATA
sprynger-0.4.1.dist-info/WHEEL
sprynger-0.4.1.dist-info/top_level.txt
sprynger-0.4.1.dist-info/RECORD
