Metadata-Version: 2.4
Name: sprynger
Version: 0.4.1
Summary: An API wrapper for Springer Nature
Author-email: "Nils A. Herrmann de Alba" <nils_herrmann@outlook.de>
License: MIT
Project-URL: Homepage, https://github.com/nils-herrmann/sprynger
Project-URL: Issues, https://github.com/nils-herrmann
Project-URL: Documentation, https://sprynger.readthedocs.io/en/latest/
Keywords: API,Springer,wrapper,requests,lxml
Classifier: Programming Language :: Python :: 3
Classifier: License :: OSI Approved :: MIT License
Classifier: Operating System :: OS Independent
Requires-Python: >=3.9
License-File: LICENSE
Requires-Dist: lxml
Requires-Dist: requests
Requires-Dist: urllib3
Requires-Dist: platformdirs
Requires-Dist: tomli>=1.2.3; python_version < "3.11"
Provides-Extra: dev
Requires-Dist: pytest; extra == "dev"
Requires-Dist: pytest-cov; extra == "dev"
Dynamic: license-file
